gamecards.py
gamecards-1.1.0.dist-info/LICENSE.txt
gamecards-1.1.0.dist-info/METADATA
gamecards-1.1.0.dist-info/WHEEL
gamecards-1.1.0.dist-info/entry_points.txt
gamecards-1.1.0.dist-info/top_level.txt
gamecards-1.1.0.dist-info/RECORD
