Metadata-Version: 2.1
Name: gamecards
Version: 1.1.0
Summary: Convert a CSV file into HTML pages of cards, for subsequent printing
Home-page: https://github.com/encodis/gamecards
Author: Philip Hodder
Author-email: philip.hodder@encodis.com
License: MIT
Keywords: gamecards cards games playing
Platform: UNKNOWN
Classifier: License :: OSI Approved :: MIT License
Classifier: Programming Language :: Python :: 3.6
Classifier: Programming Language :: Python :: 3.7
Classifier: Topic :: Games/Entertainment :: Role-Playing
